subtitleDownloader/__init__.py
subtitleDownloader/cli.py
subtitleDownloader/downloader.py
subtitleDownloader-0.1.dist-info/LICENSE
subtitleDownloader-0.1.dist-info/METADATA
subtitleDownloader-0.1.dist-info/WHEEL
subtitleDownloader-0.1.dist-info/entry_points.txt
subtitleDownloader-0.1.dist-info/top_level.txt
subtitleDownloader-0.1.dist-info/RECORD
